[{"methodName":"launchBrowser","args":[]},{"methodName":"navigateTo","args":["https://microsoftedge.github.io/Demos/demo-to-do/"]},{"methodName":"getHtmlSource","args":[]},{"methodName":"setInputValue","args":["#new-task","Feed the dog","firstTaskInput"],"variables":["firstTaskInput"]},{"methodName":"clickElement","args":["input[type='submit']","submitButton"],"variables":["submitButton"]},{"methodName":"setInputValue","args":["#new-task","Learn to code","secondTaskInput"],"variables":["secondTaskInput"]},{"methodName":"clickElement","args":["input[type='submit']","submitButton"],"variables":["submitButton"]},{"methodName":"setInputValue","args":["#new-task","Cook dinner","thirdTaskInput"],"variables":["thirdTaskInput"]},{"methodName":"clickElement","args":["input[type='submit']","submitButton"],"variables":["submitButton"]},{"methodName":"getHtmlSource","args":[]}]